nlp2sql/__init__.py
nlp2sql/cli.py
nlp2sql/adapters/__init__.py
nlp2sql/adapters/anthropic_adapter.py
nlp2sql/adapters/gemini_adapter.py
nlp2sql/adapters/local_embedding_adapter.py
nlp2sql/adapters/openai_adapter.py
nlp2sql/adapters/openai_embedding_adapter.py
nlp2sql/adapters/postgres_repository.py
nlp2sql/adapters/redshift_adapter.py
nlp2sql/config/__init__.py
nlp2sql/config/settings.py
nlp2sql/core/__init__.py
nlp2sql/core/entities.py
nlp2sql/exceptions/__init__.py
nlp2sql/factories/__init__.py
nlp2sql/factories/repository_factory.py
nlp2sql/ports/__init__.py
nlp2sql/ports/ai_provider.py
nlp2sql/ports/cache.py
nlp2sql/ports/embedding_provider.py
nlp2sql/ports/query_optimizer.py
nlp2sql/ports/schema_repository.py
nlp2sql/ports/schema_strategy.py
nlp2sql/schema/__init__.py
nlp2sql/schema/analyzer.py
nlp2sql/schema/embedding_manager.py
nlp2sql/schema/example_loader.py
nlp2sql/schema/example_store.py
nlp2sql/schema/manager.py
nlp2sql/services/__init__.py
nlp2sql/services/query_service.py
nlp2sql/utils/__init__.py
nlp2sql-0.2.0rc5.dist-info/METADATA
nlp2sql-0.2.0rc5.dist-info/WHEEL
nlp2sql-0.2.0rc5.dist-info/entry_points.txt
nlp2sql-0.2.0rc5.dist-info/licenses/LICENSE
nlp2sql-0.2.0rc5.dist-info/RECORD
