Metadata-Version: 2.4
Name: nlp2sql
Version: 0.2.0rc5
Summary: Enterprise-ready Natural Language to SQL converter with multi-provider support. Built for production scale (1000+ tables) with Clean Architecture.
Project-URL: Homepage, https://github.com/luiscarbonel1991/nlp2sql
Project-URL: Bug Tracker, https://github.com/luiscarbonel1991/nlp2sql/issues
Project-URL: Documentation, https://nlp2sql.readthedocs.io
Author-email: luiscarbonel1991 <devhighlevel@gmail.com>
License: MIT
License-File: LICENSE
Keywords: ai,clean-architecture,database,enterprise,llm,multi-provider,mysql,natural-language,nlp,postgres,production,query-generation,schema-filtering,sql
Classifier: Development Status :: 4 - Beta
Classifier: Intended Audience :: Developers
Classifier: License :: OSI Approved :: MIT License
Classifier: Programming Language :: Python :: 3
Classifier: Programming Language :: Python :: 3.9
Classifier: Programming Language :: Python :: 3.10
Classifier: Programming Language :: Python :: 3.11
Classifier: Programming Language :: Python :: 3.12
Classifier: Topic :: Database
Classifier: Topic :: Scientific/Engineering :: Artificial Intelligence
Classifier: Topic :: Software Development :: Libraries :: Python Modules
Requires-Python: >=3.9
Requires-Dist: anthropic>=0.18.0
Requires-Dist: asyncpg>=0.29.0
Requires-Dist: azure-identity>=1.15.0
Requires-Dist: boto3>=1.34.0
Requires-Dist: click>=8.0.0
Requires-Dist: faiss-cpu>=1.7.4
Requires-Dist: google-generativeai>=0.3.0
Requires-Dist: greenlet>=3.2.3
Requires-Dist: httpx>=0.25.0
Requires-Dist: numpy>=1.24.0
Requires-Dist: openai>=1.0.0
Requires-Dist: pandas>=2.0.0
Requires-Dist: psycopg2-binary>=2.9.0
Requires-Dist: psycopg[binary]>=3.2.13
Requires-Dist: pydantic-settings>=2.0.0
Requires-Dist: pydantic>=2.5.0
Requires-Dist: redis>=5.0.0
Requires-Dist: scikit-learn>=1.3.0
Requires-Dist: sqlalchemy-redshift>=0.7.0
Requires-Dist: sqlalchemy>=2.0.0
Requires-Dist: structlog>=24.1.0
Requires-Dist: tenacity>=8.2.0
Requires-Dist: tiktoken>=0.5.0
Provides-Extra: all-embeddings
Requires-Dist: sentence-transformers>=2.5.0; extra == 'all-embeddings'
Provides-Extra: all-providers
Requires-Dist: anthropic>=0.18.0; extra == 'all-providers'
Requires-Dist: google-generativeai>=0.3.0; extra == 'all-providers'
Provides-Extra: anthropic
Requires-Dist: anthropic>=0.18.0; extra == 'anthropic'
Provides-Extra: dev
Requires-Dist: black>=23.7.0; extra == 'dev'
Requires-Dist: isort>=5.12.0; extra == 'dev'
Requires-Dist: mypy>=1.7.0; extra == 'dev'
Requires-Dist: myst-parser>=2.0.0; extra == 'dev'
Requires-Dist: pytest-asyncio>=0.21.0; extra == 'dev'
Requires-Dist: pytest-cov>=4.1.0; extra == 'dev'
Requires-Dist: pytest-mock>=3.11.0; extra == 'dev'
Requires-Dist: pytest>=7.4.0; extra == 'dev'
Requires-Dist: ruff>=0.1.0; extra == 'dev'
Requires-Dist: sphinx-rtd-theme>=1.3.0; extra == 'dev'
Requires-Dist: sphinx>=7.0.0; extra == 'dev'
Provides-Extra: embeddings-local
Requires-Dist: sentence-transformers>=2.5.0; extra == 'embeddings-local'
Provides-Extra: embeddings-openai
Provides-Extra: gemini
Requires-Dist: google-generativeai>=0.3.0; extra == 'gemini'
Provides-Extra: mssql
Requires-Dist: pymssql>=2.2.0; extra == 'mssql'
Provides-Extra: mysql
Requires-Dist: mysql-connector-python>=8.0.0; extra == 'mysql'
Requires-Dist: pymysql>=1.1.0; extra == 'mysql'
Provides-Extra: oracle
Requires-Dist: oracledb>=2.0.0; extra == 'oracle'
